LICENSE
README.md
setup.py
haostart/1.py
haostart/__init__.py
haostart/test.py
haostart.egg-info/PKG-INFO
haostart.egg-info/SOURCES.txt
haostart.egg-info/dependency_links.txt
haostart.egg-info/requires.txt
haostart.egg-info/top_level.txt