Metadata-Version: 1.0
Name: haostart
Version: 1.0.2
Summary: Haostart-Self_Tools
Home-page: https://gitee.com/haostart/dashboard/projects
Author: haostart
Author-email: haostart@hotmail.com
License: Apache License
Platform: UNKNOWN
